{
  "site": {
    "title": "Ibada Cloud",
    "description": "Ibada Cloud helps churches manage members, branches, activities, finances, forms, and day-to-day operations from one structured platform.",
    "url": "https://www.ibadacloud.com"
  },
  "navigation": {
    "links": [
      { "label": "Home", "href": "/" },
      { "label": "Platform", "href": "/platform" },
      { "label": "Solutions", "href": "/solutions" },
      { "label": "Guides", "href": "/guides" },
      { "label": "Pricing", "href": "/compare/church-management-software-pricing" },
      { "label": "Contact", "href": "/#contact" }
    ],
    "cta": {
      "label": "Request a demo",
      "href": "mailto:hello@ibadacloud.com?subject=Ibada%20Cloud%20-%20Request%20a%20demo"
    },
    "mobileMenuLabel": "Menu",
    "mobileCloseLabel": "Close menu"
  },
  "hero": {
    "eyebrow": "Church operations, simplified",
    "headline": "Run your church with clarity not clutter.",
    "description": "Ibada Cloud brings members, branches, activities, finances, and Smart Forms into one operating layer. Built for teams that need structure, not another scattered inbox.",
    "primaryCta": {
      "label": "Request a demo",
      "href": "mailto:hello@ibadacloud.com?subject=Ibada%20Cloud%20-%20Request%20a%20demo"
    },
    "secondaryCta": {
      "label": "View pricing",
      "href": "/compare/church-management-software-pricing"
    },
    "tertiaryCta": {
      "label": "Read the software evaluation guide",
      "href": "/guides/how-to-choose-church-management-software"
    },
    "focusPoints": [
      {
        "title": "Structured membership",
        "body": "Households, branches, and pastoral context stay organized as you grow."
      },
      {
        "title": "Operations & finances",
        "body": "Activities, categories, and reporting that fits how churches actually work."
      },
      {
        "title": "Smart Forms",
        "body": "Collect information once, route it cleanly, and reduce follow-up threads."
      }
    ]
  },
  "about": {
    "id": "about",
    "eyebrow": "About",
    "title": "Software shaped around how churches actually operate",
    "lead": "Ibada Cloud replaces scattered tools and ad hoc workflows with one structured layer, so leaders see what matters and teams spend less time reconciling data.",
    "body": "We focus on membership, branches, activities, money in and out, and repeatable intake through Smart Forms. You get clear objects and sensible limits by plan, plus exports when you need to work offline or share with finance volunteers and accountants.",
    "highlights": [
      {
        "title": "Purpose-built",
        "body": "Flows reflect parishes and multi-site churches, not generic “accounts.”"
      },
      {
        "title": "Honest pricing",
        "body": "Transparent tiers so you can plan ahead as attendance and branches grow."
      },
      {
        "title": "Humans behind the product",
        "body": "Talk to us by email for demos, onboarding, and day-to-day support."
      }
    ]
  },
  "pricing": {
    "id": "pricing",
    "title": "Pricing that fits your church stage",
    "subtitle": "Four clear options with simple limits and capabilities.",
    "featureLabels": {
      "included": "Included",
      "notIncluded": "Not included",
      "note": "Note"
    },
    "plans": [
      {
        "id": "essential",
        "name": "Essential",
        "priceDisplay": "$14.99",
        "priceNote": "/ month",
        "tagline": "Single-branch starter",
        "description": "For small single branch churches.",
        "popular": false,
        "accent": "green",
        "includedFeatures": [
          "1 branch",
          "Up to 250 members",
          "Up to 2 Smart Forms",
          "Member profiles",
          "Activities and attendance",
          "Assets",
          "Basic income and expense tracking",
          "Simple income and expense categories",
          "Basic dashboard overview",
          "Lightweight reports",
          "Email support"
        ],
        "excludedFeatures": [
          "Pledges and campaigns",
          "Budgeting",
          "Advanced reports",
          "Advanced export",
          "Multi branch management",
          "Parish context",
          "Remittance"
        ],
        "cta": {
          "label": "Request a demo",
          "href": "mailto:hello@ibadacloud.com?subject=Ibada%20Cloud%20-%20Essential"
        }
      },
      {
        "id": "growth",
        "name": "Growth",
        "priceDisplay": "$39.99",
        "priceNote": "/ month",
        "tagline": "Growing church operations",
        "description": "For growing churches and small multi branch setups.",
        "popular": true,
        "popularLabel": "Popular",
        "accent": "orange",
        "includedFeatures": [
          "Up to 5 branches",
          "Up to 2,000 members",
          "Up to 20 Smart Forms",
          "Pledges and campaigns",
          "Basic budgeting",
          "Advanced finance categories",
          "CSV and Excel export",
          "Monthly summaries",
          "Branch-level permissions",
          "User invitations and access management",
          "Everything in Essential"
        ],
        "note": "Additional branches: $10/month each",
        "cta": {
          "label": "Request a demo",
          "href": "mailto:hello@ibadacloud.com?subject=Ibada%20Cloud%20-%20Growth"
        }
      },
      {
        "id": "scale",
        "name": "Scale",
        "priceDisplay": "$59.99",
        "priceNote": "/ month",
        "tagline": "Parish leadership and larger teams",
        "description": "For parish leadership and larger multi branch churches.",
        "popular": false,
        "accent": "green",
        "includedFeatures": [
          "Up to 10 branches",
          "Up to 10,000 members",
          "Unlimited Smart Forms",
          "Parish context",
          "Branch and parish finance",
          "Remittance support",
          "Advanced budgeting",
          "Advanced financial reports",
          "Monthly and yearly summaries",
          "Category breakdowns and trends",
          "Advanced export",
          "Priority support",
          "Everything in Growth"
        ],
        "note": "Additional branches: $10/month each",
        "cta": {
          "label": "Request a demo",
          "href": "mailto:hello@ibadacloud.com?subject=Ibada%20Cloud%20-%20Scale"
        }
      },
      {
        "id": "custom",
        "name": "Custom",
        "priceDisplay": "Custom pricing",
        "priceNote": "",
        "tagline": "Parish networks and complex rollouts",
        "description": "For large parish networks, assisted migration, training, dedicated onboarding, or special reporting needs.",
        "popular": false,
        "accent": "green",
        "includedFeatures": [
          "More than 10 branches",
          "Data migration",
          "Team training",
          "Custom onboarding",
          "Special reporting needs",
          "Priority support",
          "Rollout assistance"
        ],
        "cta": {
          "label": "Contact us",
          "href": "mailto:hello@ibadacloud.com?subject=Ibada%20Cloud%20-%20Custom%20plan"
        }
      }
    ]
  },
  "pricingComparison": {
    "id": "compare",
    "title": "Compare plans in detail",
    "subtitle": "Compare Essential, Growth, and Scale side by side.",
    "mobileScrollHint": "Review each capability across the three standard plans.",
    "featureColumnLabel": "Capability",
    "recommendedLabel": "Popular",
    "planColumnLabels": ["Essential", "Growth", "Scale"],
    "planColumnIds": ["essential", "growth", "scale"],
    "smartFormsNote": {
      "label": "Smart Forms (overview)",
      "format": "text",
      "values": {
        "essential": "Up to 2 Smart Forms",
        "growth": "Up to 20 Smart Forms",
        "scale": "Unlimited forms with the same structured intake."
      }
    },
    "rows": [
      {
        "label": "Members limit",
        "format": "text",
        "values": { "essential": "250", "growth": "2,000", "scale": "10,000" }
      },
      {
        "label": "Branches limit",
        "format": "text",
        "values": { "essential": "1", "growth": "5", "scale": "10" }
      },
      {
        "label": "Form limit",
        "format": "text",
        "values": { "essential": "2", "growth": "20", "scale": "Unlimited" }
      },
      {
        "label": "Member profiles",
        "format": "boolean",
        "values": { "essential": true, "growth": true, "scale": true }
      },
      {
        "label": "Activities and attendance",
        "format": "boolean",
        "values": { "essential": true, "growth": true, "scale": true }
      },
      {
        "label": "Assets",
        "format": "boolean",
        "values": { "essential": true, "growth": true, "scale": true }
      },
      {
        "label": "Basic income and expense tracking",
        "format": "boolean",
        "values": { "essential": true, "growth": true, "scale": true }
      },
      {
        "label": "Simple income and expense categories",
        "format": "boolean",
        "values": { "essential": true, "growth": true, "scale": true }
      },
      {
        "label": "Basic dashboard overview",
        "format": "boolean",
        "values": { "essential": true, "growth": true, "scale": true }
      },
      {
        "label": "Lightweight reports",
        "format": "boolean",
        "values": { "essential": true, "growth": true, "scale": true }
      },
      {
        "label": "Pledges",
        "format": "boolean",
        "values": { "essential": false, "growth": true, "scale": true }
      },
      {
        "label": "Campaigns",
        "format": "boolean",
        "values": { "essential": false, "growth": true, "scale": true }
      },
      {
        "label": "Budgeting",
        "format": "boolean",
        "values": { "essential": false, "growth": true, "scale": true }
      },
      {
        "label": "Advanced finance categories",
        "format": "boolean",
        "values": { "essential": false, "growth": true, "scale": true }
      },
      {
        "label": "CSV and Excel export",
        "format": "boolean",
        "values": { "essential": false, "growth": true, "scale": true }
      },
      {
        "label": "Monthly summaries",
        "format": "boolean",
        "values": { "essential": false, "growth": true, "scale": true }
      },
      {
        "label": "Branch-level permissions",
        "format": "boolean",
        "values": { "essential": false, "growth": true, "scale": true }
      },
      {
        "label": "User invitations and access management",
        "format": "boolean",
        "values": { "essential": false, "growth": true, "scale": true }
      },
      {
        "label": "Multi branch management",
        "format": "boolean",
        "values": { "essential": false, "growth": true, "scale": true }
      },
      {
        "label": "Parish context",
        "format": "boolean",
        "values": { "essential": false, "growth": false, "scale": true }
      },
      {
        "label": "Branch and parish finance",
        "format": "boolean",
        "values": { "essential": false, "growth": false, "scale": true }
      },
      {
        "label": "Remittance support",
        "format": "boolean",
        "values": { "essential": false, "growth": false, "scale": true }
      },
      {
        "label": "Advanced financial reports",
        "format": "boolean",
        "values": { "essential": false, "growth": false, "scale": true }
      },
      {
        "label": "Monthly and yearly summaries",
        "format": "boolean",
        "values": { "essential": false, "growth": false, "scale": true }
      },
      {
        "label": "Category breakdowns and trends",
        "format": "boolean",
        "values": { "essential": false, "growth": false, "scale": true }
      },
      {
        "label": "Advanced export",
        "format": "boolean",
        "values": { "essential": false, "growth": false, "scale": true }
      },
      {
        "label": "Priority support",
        "format": "boolean",
        "values": { "essential": false, "growth": false, "scale": true }
      }
    ]
  },
  "cta": {
    "title": "Ready to organize your church operations?",
    "description": "Request a demo and see how Ibada Cloud can support your church.",
    "primaryCta": {
      "label": "Request a demo",
      "href": "mailto:hello@ibadacloud.com?subject=Ibada%20Cloud%20-%20Request%20a%20demo"
    },
    "secondaryCta": {
      "label": "Read buying guides",
      "href": "/guides"
    }
  },
  "contact": {
    "metaTitle": "Contact",
    "metaDescription": "Get in touch with Ibada Cloud, demos, pricing questions, and support for church operations.",
    "eyebrow": "Contact",
    "title": "Let's talk about your church operations",
    "description": "Request a demo, ask about pricing, or share what you're trying to solve. We read every message and reply as soon as we can.",
    "directLabel": "Email us directly",
    "responseBlurb": "We usually respond within one to two business days. For urgent issues, mention it in your message.",
    "bullets": [
      "Demos tailored to your team and current tools",
      "Guidance on plans, limits, and rollout",
      "Questions about security, data, and support"
    ],
    "pricingPrompt": "Prefer to skim numbers first?",
    "pricingLinkLabel": "View pricing on the homepage",
    "formCardTitle": "Send a message",
    "formCardSubtitle": "Share a few details and we'll follow up by email. No spam, just a conversation.",
    "form": {
      "mailtoSubject": "Ibada Cloud, Contact form",
      "nameLabel": "Name",
      "emailLabel": "Email",
      "organizationLabel": "Church or organization",
      "messageLabel": "How can we help?",
      "submitLabel": "Compose in email",
      "note": "This opens your email app with your message filled in. You can edit before sending.",
      "validationHint": "Please add your email and a short message so we can reply."
    }
  },
  "footer": {
    "id": "footer",
    "description": "Ibada Cloud is a structured platform for members, branches, activities, finance, Smart Forms, and church operations.",
    "contactEmail": "hello@ibadacloud.com",
    "contactLabel": "Email",
    "backToTopLabel": "Back to top",
    "links": [
      { "label": "Home", "href": "/" },
      { "label": "Platform", "href": "/platform" },
      { "label": "Solutions", "href": "/solutions" },
      { "label": "Guides", "href": "/guides" },
      { "label": "Pricing", "href": "/compare/church-management-software-pricing" },
      { "label": "Contact", "href": "/#contact" },
      {
        "label": "Request a demo",
        "href": "mailto:hello@ibadacloud.com?subject=Ibada%20Cloud%20-%20Request%20a%20demo"
      }
    ],
    "copyright": "© {year} Ibada Cloud. All rights reserved."
  }
}
